[
  {
    "model_family": "hybrid_tcn_lstm",
    "status": "completed",
    "test_accuracy": 0.9353746978243352,
    "test_macro_precision": 0.2788753900887322,
    "test_macro_recall": 0.2662747696579578,
    "test_macro_f1": 0.25704885199085936,
    "test_weighted_f1": 0.9101729966840523,
    "test_balanced_accuracy": 0.2662747696579578,
    "cv_mean_val_accuracy": null,
    "cv_mean_val_macro_precision": null,
    "cv_mean_val_macro_recall": null,
    "cv_mean_val_macro_f1": null,
    "cv_mean_val_weighted_f1": null,
    "cv_mean_val_balanced_accuracy": null,
    "cv_std_val_accuracy": null,
    "cv_std_val_macro_precision": null,
    "cv_std_val_macro_recall": null,
    "cv_std_val_macro_f1": null,
    "cv_std_val_weighted_f1": null,
    "cv_std_val_balanced_accuracy": null,
    "epochs_last_run": 10,
    "temporal_pair_count": 0,
    "temporal_pairs": "",
    "removed_classes": "INDUSTRIAL CONTROL AND AUTOMATION ENGINEERING, TEXTILE ENGINEERING"
  },
  {
    "model_family": "ft_transformer_gru_attention",
    "status": "completed",
    "test_accuracy": 0.9332796132151491,
    "test_macro_precision": 0.2635256544312419,
    "test_macro_recall": 0.26758144992827404,
    "test_macro_f1": 0.2604666817215766,
    "test_weighted_f1": 0.9109504525329407,
    "test_balanced_accuracy": 0.26758144992827404,
    "cv_mean_val_accuracy": null,
    "cv_mean_val_macro_precision": null,
    "cv_mean_val_macro_recall": null,
    "cv_mean_val_macro_f1": null,
    "cv_mean_val_weighted_f1": null,
    "cv_mean_val_balanced_accuracy": null,
    "cv_std_val_accuracy": null,
    "cv_std_val_macro_precision": null,
    "cv_std_val_macro_recall": null,
    "cv_std_val_macro_f1": null,
    "cv_std_val_weighted_f1": null,
    "cv_std_val_balanced_accuracy": null,
    "epochs_last_run": 10,
    "temporal_pair_count": 0,
    "temporal_pairs": "",
    "removed_classes": "INDUSTRIAL CONTROL AND AUTOMATION ENGINEERING, TEXTILE ENGINEERING"
  },
  {
    "model_family": "xgboost_temporal_gru",
    "status": "completed",
    "test_accuracy": 0.9318291700241741,
    "test_macro_precision": 0.27928565887952644,
    "test_macro_recall": 0.27213545470981093,
    "test_macro_f1": 0.2682308156961982,
    "test_weighted_f1": 0.9119153723619806,
    "test_balanced_accuracy": 0.27213545470981093,
    "cv_mean_val_accuracy": null,
    "cv_mean_val_macro_precision": null,
    "cv_mean_val_macro_recall": null,
    "cv_mean_val_macro_f1": null,
    "cv_mean_val_weighted_f1": null,
    "cv_mean_val_balanced_accuracy": null,
    "cv_std_val_accuracy": null,
    "cv_std_val_macro_precision": null,
    "cv_std_val_macro_recall": null,
    "cv_std_val_macro_f1": null,
    "cv_std_val_weighted_f1": null,
    "cv_std_val_balanced_accuracy": null,
    "epochs_last_run": 10,
    "temporal_pair_count": 0,
    "temporal_pairs": "",
    "removed_classes": "INDUSTRIAL CONTROL AND AUTOMATION ENGINEERING, TEXTILE ENGINEERING"
  },
  {
    "model_family": "deepfm_temporal_tcn",
    "status": "completed",
    "test_accuracy": 0.934085414987913,
    "test_macro_precision": 0.2509013005025791,
    "test_macro_recall": 0.2639793304675145,
    "test_macro_f1": 0.2538184804871269,
    "test_weighted_f1": 0.9097847086883838,
    "test_balanced_accuracy": 0.2639793304675145,
    "cv_mean_val_accuracy": null,
    "cv_mean_val_macro_precision": null,
    "cv_mean_val_macro_recall": null,
    "cv_mean_val_macro_f1": null,
    "cv_mean_val_weighted_f1": null,
    "cv_mean_val_balanced_accuracy": null,
    "cv_std_val_accuracy": null,
    "cv_std_val_macro_precision": null,
    "cv_std_val_macro_recall": null,
    "cv_std_val_macro_f1": null,
    "cv_std_val_weighted_f1": null,
    "cv_std_val_balanced_accuracy": null,
    "epochs_last_run": 10,
    "temporal_pair_count": 0,
    "temporal_pairs": "",
    "removed_classes": "INDUSTRIAL CONTROL AND AUTOMATION ENGINEERING, TEXTILE ENGINEERING"
  }
]